{
  "@type": "http://data.odeuropa.eu/ontology/L11_Smell",
  "@id": "http://data.odeuropa.eu/smell/c1521cc7-3a68-5dab-886f-ac729ef79c55",
  "@graph": "http://data.odeuropa.eu/gallica",
  "label": "odeur",
  "source": {
    "@id": "http://data.odeuropa.eu/source/ff7a63d6-dc8a-598c-8ac3-159245d0bec9",
    "excerpts": [
      {
        "@id": "http://data.odeuropa.eu/source/ff7a63d6-dc8a-598c-8ac3-159245d0bec9/fragment/0346d170-67b3-530d-9c8d-b402e0acc1d8",
        "value": "Ces chiffres sont notoirement inférieurs à la réalité .Le commerce des parfums est accaparé à Constantinople par la maison Orosdi - Back , qui les réexpédie dans le reste de 1 Empire .( B .",
        "words": [
          "parfums",
          "Constantinople"
        ]
      },
      {
        "@id": "http://data.odeuropa.eu/source/ff7a63d6-dc8a-598c-8ac3-159245d0bec9/fragment/09989186-4e80-54a9-803f-88e77a4d07c2",
        "value": "Les simiths sont de petits gâteaux ronds , en farine de froment , évidés au milieu , qu ' on roule dans des graines de sésame décortiquées et qu ’ on fait ensuite cuire au four .Le sésame cuit donne à la pâte une saveur particulière qui est , paraît - il , fort agréable .Seulement il faut manger le simith tout frais : au bout d une demi - journée , il sent ie rance .",
        "words": [
          "particulière",
          "fort agréable",
          "pâte",
          "saveur"
        ]
      },
      {
        "@id": "http://data.odeuropa.eu/source/ff7a63d6-dc8a-598c-8ac3-159245d0bec9/fragment/0eefeca7-e6f6-5060-902a-60296b8bc259",
        "value": "2 Entièrement exportés par navires français .Les baumes sont des sucs végétaux , qui , spontanément ou par incision , découlent de certains arbres , plantes ou arbustes , et qui contiennent un acide aromatique .Les principaux sont : 1e baume de tolu , de copahu .",
        "words": [
          "plantes",
          "arbres",
          "baumes",
          "acide aromatique",
          "sucs végétaux"
        ]
      },
      {
        "@id": "http://data.odeuropa.eu/source/ff7a63d6-dc8a-598c-8ac3-159245d0bec9/fragment/1964cc13-de78-5c6d-a974-e111529ea238",
        "value": "Aujourd ’ hui encore , les Musulmans s ’ aspergent d ’ eau de rose dans certaines cérémonies pieuses et de famille , les orthodoxes brûlent de l ’ encens devant les icônes , les femmes se couvrent le visage de poudre de riz et les hommes se teignent la moustache .Les parfums étrangers et particulièrement les parfums français se vendent dans les grandes villes ; mais , dans les cités de moindre importance et dans les localités les plus éloignées de 1 Empire , on préfère la parfumerie indigène .Suivant les régions , on obtient diverses huiles des plantes aromatiques , telles que le thym , la sauge et l ' origan ; on extrait des essences de la rose ou de la tleur d ’ oranger : à Rhodes , un arbre nommé styrax , de la > grandeur du chêne , laisse exsuder une résine qui se vend sous le nom d ' huile de styrax ; à Cliio , le mastic , qu ’ on emploie à parfumer le raki , sert aussi de dentifrice , ; ailleurs , on utilise la lavande et les cassies pour donner une bonne odeur au linge ; le henné , qui vient d ' Orfa , sert à colorer les cheveux et les ongles ; on parfume les chambres avec de l ' écorce d ’ ambre et l ’ on conserve les fourrures dans des caisses de bois de cyprès .",
        "words": [
          "parfums",
          "parfumerie"
        ]
      },
      {
        "@id": "http://data.odeuropa.eu/source/ff7a63d6-dc8a-598c-8ac3-159245d0bec9/fragment/1cf00dab-2c51-5196-a0e2-cff096ea42b1",
        "value": "VIII .JLes espèce » médicinales .— Réglisse , saponaire , casse , semen - contra .",
        "words": "médicinales"
      },
      {
        "@id": "http://data.odeuropa.eu/source/ff7a63d6-dc8a-598c-8ac3-159245d0bec9/fragment/2217306c-57f7-502d-bf33-194a5ea6d0f0",
        "value": "La reine de Saba en apportait à Salomon et les rois mages en faisaient hommage au Seigneur naissant .Les parfums d ’ Orient sont presque toujours employés à l ’ état naturel .Les plus usités sont : L ’ encens , dont on fait un très grand usage dans les cérémonies religieuses ; La pastille odoriférante , faite avec du bois d ' aloès , du bois de santal et de l ' oliban .",
        "words": [
          "parfums",
          "Orient"
        ]
      },
      {
        "@id": "http://data.odeuropa.eu/source/ff7a63d6-dc8a-598c-8ac3-159245d0bec9/fragment/2e5f773f-3d1c-5746-8bb8-1824f06e66d1",
        "value": "On en distingue deux sortes commerciales : le semen - contra d ’ Alep , verdâtre ou jaune rougeâtre , et le semen - contra de Barbarie , plus répandu mais moins estimé .Le principe actif du semen - contra est la santonine , substance blanche , sans saveur ni odeur , qui est un vermifuge d ' un emploi très usité , surtout pour les enfants .La coque du Levant est le fruit du menispermum cocculus , arbuste qui croît en Asie Mineure .",
        "words": [
          "odeur",
          "substance blanche",
          "vermifuge",
          "santonine"
        ]
      },
      {
        "@id": "http://data.odeuropa.eu/source/ff7a63d6-dc8a-598c-8ac3-159245d0bec9/fragment/33b52423-b961-594d-a793-6009fb29bd89",
        "value": "C ' est le baume par excellence ; les Grecs lui avaient donné le nom de / 3On le trouve , dès la plus haute antiquité , en Judée , d ' où il a disparu ; puis en Egypte , d ' où il a également disparu , et enfin en Arabie , où il croît aujourd ’ hui aux environs de la Mecque et de Médine .Ce baume , de couleur blanche , possède une odeur forte , aromatique et agréable .Il doit être conservé dans des vases de plomb ou dans des flacons de cristal bouchant à l ' émeri .",
        "words": [
          "aromatique",
          "agréable",
          "forte",
          "odeur",
          "baume"
        ]
      },
      {
        "@id": "http://data.odeuropa.eu/source/ff7a63d6-dc8a-598c-8ac3-159245d0bec9/fragment/35d8bc5b-6684-5c22-a7c3-a0ccd877ba61",
        "value": "210 quintaux ont été importés par navires français , 83 par navires étrangers , et 1 par voie de terre .L ' Orient est le pays des parfums .Aussi loin qu ' on peut remonter , dans l ' histoire , on en trouve l ' emploi dans la vie domestique et dans les fêtes civiles et reli - IMPORTATIONS DE FRANCE EN TURQUIE 546 gieuses .",
        "words": [
          "parfums",
          "Orient"
        ]
      },
      {
        "@id": "http://data.odeuropa.eu/source/ff7a63d6-dc8a-598c-8ac3-159245d0bec9/fragment/39407f56-131b-5af7-a61f-b843e5a67f71",
        "value": "On en distingue deux sortes commerciales : le semen - contra d ’ Alep , verdâtre ou jaune rougeâtre , et le semen - contra de Barbarie , plus répandu mais moins estimé .Le principe actif du semen - contra est la santonine , substance blanche , sans saveur ni odeur , qui est un vermifuge d ’ un emploi très usité , surtout pour les enfants .La coque du Levant est le fruit du menispermum cocculus , arbuste qui croît en Asie Mineure .",
        "words": [
          "odeur",
          "substance blanche",
          "vermifuge",
          "santonine"
        ]
      },
      {
        "@id": "http://data.odeuropa.eu/source/ff7a63d6-dc8a-598c-8ac3-159245d0bec9/fragment/455dd951-9fa8-58ef-a0d6-cf6175b8b6e0",
        "value": "On les mélange avec des graisses et huiles diverses , telles que huiles de lin , de soleil , de coton , d ' arachides ou autres .Le tout est coloré avec du cucurma , du poivre rouge ou autres matières colorantes et coulé , pour l ' exportation , dans des barils de 100 à 5oo kilogrammes .Ce nouveau produit , qui usurpe le nom de beurre , n est en réalité que de la graisse .",
        "words": [
          "matières",
          "colorantes",
          "poivre rouge"
        ]
      },
      {
        "@id": "http://data.odeuropa.eu/source/ff7a63d6-dc8a-598c-8ac3-159245d0bec9/fragment/45e61003-50e4-5896-8e62-d0eff3e128fd",
        "value": "7 114 Entièrement exportés par navires français .Les baumes sont des sucs végétaux , qui , spontanément ou par incision , découlent de certains arbres , plantes ou arbustes , et qui contiennent un acide aromatique .Les principaux sont : 1e baume de tolu , de copahu , le baume du Pérou , le baume de la Mecque et le baume du Canada .",
        "words": [
          "plantes",
          "arbres",
          "baumes",
          "acide aromatique",
          "sucs végétaux"
        ]
      },
      {
        "@id": "http://data.odeuropa.eu/source/ff7a63d6-dc8a-598c-8ac3-159245d0bec9/fragment/6254b4f6-d3cf-51f0-ac18-e8fed608e772",
        "value": "Les parfums d ’ Orient sont presque toujours employés à l ’ état naturel .Les plus usités sont : L ’ encens , dont on fait un très grand usage dans les cérémonies religieuses ; La pastille odoriférante , faite avec du bois d ' aloès , du bois de santal et de l ' oliban .Le tout est réduit en poudre , mis en pâte , puis solidifié à l ’ aide d ' une résine .",
        "words": [
          "encens",
          "odoriférante",
          "pastille",
          "aloès",
          "bois d",
          "bois de santal"
        ]
      },
      {
        "@id": "http://data.odeuropa.eu/source/ff7a63d6-dc8a-598c-8ac3-159245d0bec9/fragment/7358244c-0dc8-57ef-9537-248cc793825c",
        "value": "Le sésame cuit donne à la pâte une saveur particulière qui est , paraît - il , fort agréable .Seulement il faut manger le simith tout frais : au bout d une demi - journée , il sent ie rance .Le simith vaut un sou .",
        "words": [
          "rance",
          "sent",
          "simith",
          "bout d une demi - journée"
        ]
      },
      {
        "@id": "http://data.odeuropa.eu/source/ff7a63d6-dc8a-598c-8ac3-159245d0bec9/fragment/7487afd3-3e3e-56f7-b08a-60352d0e1b1a",
        "value": "Le fenouil est une plante de la famille des ombelli - fères , qui croît de préférence dans les endroits secs et 280 EXPORTATIONS DU LEVANT EN FRANCE pierreux .Son odeur est aromatique , sa saveur douce et agréable .On s ' en sert comme condiment avec les légumes et le poisson ; ses fruits renferment une huile jaune et sont utilisés dans la fabrication de l ' anisette et en médecine .",
        "words": [
          "aromatique",
          "agréable",
          "douce",
          "odeur",
          "Son",
          "sa"
        ]
      },
      {
        "@id": "http://data.odeuropa.eu/source/ff7a63d6-dc8a-598c-8ac3-159245d0bec9/fragment/75268730-3b6b-52b6-843a-66fabbc1ee63",
        "value": "Le bétail se compose comme dans nos pays des chevaux , bœufs , vaches , veaux , moutons , chèvres , et porcs , auxquels il faut joindre les buffles , appartenant à la race bovine .Comme importance , les moutons et les chèvres pas - sent avant les animaux de l ’ espèce bovine , en raison de l ’ utilisation industrielle de leur toison ou de leurs poils .L ’ élevage du mouton est pratiqué d ’ une façon singulière .",
        "words": [
          "sent",
          "moutons"
        ]
      },
      {
        "@id": "http://data.odeuropa.eu/source/ff7a63d6-dc8a-598c-8ac3-159245d0bec9/fragment/761652bb-371e-5509-aa2f-bb1b621a6783",
        "value": "L anis est , comme le fenouil , une plante de la famille des ombellifères .Les fruits ovoïdes ou piriformes ont une saveur douce , aromatique et sucrée .L ’ anis s ’ emploie en infusions , comme stimulant des voies digestives , il entre dans la composition de l ' élixir parégorique et dans la composition de certaines drogues .",
        "words": [
          "aromatique",
          "douce",
          "sucrée",
          "saveur",
          "fruits ovoïdes"
        ]
      },
      {
        "@id": "http://data.odeuropa.eu/source/ff7a63d6-dc8a-598c-8ac3-159245d0bec9/fragment/98c8c844-ff1a-5127-bb0d-ab021ec11ec3",
        "value": "Smyrne .— Les plantations de tabac augmentent d ' année en année dans le vilayet de Smyrne , qui produit environ 2 millions de kilogrammes , dont 1 million 1 / 2 de tabacs odoriférants , genre Ayassoulouk et aoo .ooo de tabacs commun genre Magnésie .",
        "words": [
          "odoriférants",
          "tabacs",
          "le vilayet de Smyrne"
        ]
      },
      {
        "@id": "http://data.odeuropa.eu/source/ff7a63d6-dc8a-598c-8ac3-159245d0bec9/fragment/9a7b2ae4-9395-53b9-aa52-2b451700d34d",
        "value": "La gomme arabique est originaire de l ’ Irak - Arabi , d ’ où lui vient son nom .Le principal centre de production est Mendélé , dans le vilayet de Bagdad Elle s ’ obtient par l ’ exsudation spontanée d ’ un arbre de la famille des légumineuses , nommé l ' acacia vera .La récolte se fait au mois d ’ août .",
        "words": [
          "acacia",
          "exsudation",
          "Mendélé",
          "dans le vilayet de Bagdad"
        ]
      },
      {
        "@id": "http://data.odeuropa.eu/source/ff7a63d6-dc8a-598c-8ac3-159245d0bec9/fragment/9ba9663a-11cc-560f-a8d4-0ded5068d0e1",
        "value": "244 891 178 .3 Autres objets Appareils inodores 1 , 5o 3i 22 3 .3 Bouderie pour sellerie et access .",
        "words": "inodores"
      },
      {
        "@id": "http://data.odeuropa.eu/source/ff7a63d6-dc8a-598c-8ac3-159245d0bec9/fragment/ca0af711-ae47-5f69-816f-0a9c8717bc15",
        "value": "Les parfums étrangers et particulièrement les parfums français se vendent dans les grandes villes ; mais , dans les cités de moindre importance et dans les localités les plus éloignées de 1 Empire , on préfère la parfumerie indigène .Suivant les régions , on obtient diverses huiles des plantes aromatiques , telles que le thym , la sauge et l ' origan ; on extrait des essences de la rose ou de la tleur d ’ oranger : à Rhodes , un arbre nommé styrax , de la > grandeur du chêne , laisse exsuder une résine qui se vend sous le nom d ' huile de styrax ; à Cliio , le mastic , qu ’ on emploie à parfumer le raki , sert aussi de dentifrice , ; ailleurs , on utilise la lavande et les cassies pour donner une bonne odeur au linge ; le henné , qui vient d ' Orfa , sert à colorer les cheveux et les ongles ; on parfume les chambres avec de l ' écorce d ’ ambre et l ’ on conserve les fourrures dans des caisses de bois de cyprès .Les fabriques locales , imitant les produits européens , font des savons , de la poudre de riz , des extraits pour le mouchoir , des eaux de Cologne qui se vendent sous des noms de fantaisie , des eaux de lavande et de toilette , des cosmétiques , des teintures pour les cheveux et la moustache , etc .",
        "words": [
          "résine",
          "bonne",
          "parfumer",
          "odeur",
          "thym",
          "mastic",
          "rose",
          "plantes",
          "chambres",
          "aromatiques",
          "parfume",
          "écorce",
          "linge",
          "lavande",
          "sauge",
          "origan",
          "Rhodes",
          "cassies",
          "Cliio"
        ]
      },
      {
        "@id": "http://data.odeuropa.eu/source/ff7a63d6-dc8a-598c-8ac3-159245d0bec9/fragment/cc370ff2-06b6-50ce-9738-048c6b371a75",
        "value": "Ces pastilles sont d ' une vente très commune en Occident , où elles sont connues sous le nom de pastilles du Sérail .On les contrefait souvent ; Le patchouli pour le mouchoir ; Le bois d ’ aloès , qui répand une odeur fort agréable lorsqu ' on le brûle dans les appartements ; Le galouk , pommade à base d ’ essence de roses ; Le rastic , pâte plus ou moins liquide , qui sert à teindre les cheveux et la barbe en noir , blond ou châtain ; Le sourmak , poudre assez adhérente , qui donne aux cils du brillant et du velouté .Enfin , le blanc pour la figure , beaucoup plus gras que celui qui est composé en Occident .",
        "words": [
          "odeur",
          "patchouli",
          "fort agréable",
          "essence de roses",
          "les appartements",
          "bois d ’ aloès"
        ]
      },
      {
        "@id": "http://data.odeuropa.eu/source/ff7a63d6-dc8a-598c-8ac3-159245d0bec9/fragment/cf269a5e-f2a9-50c4-ade0-b912c3660d3f",
        "value": "Chio produit un lentisque qui donne la gomme mastic .Cette gomme résineuse et odorante sert à parfumer les eaux de - vie indigènes .L ’ industrie est peu florissante , bille consiste en tanneries ( Rhodes , Mételin et Chio ) , dans la pèche des éponges ( Svmi et Ka - lymnos ) , la fabrication des huiles d ’ olives ( Chio et Mélel in ) , celle des vins et eaux - de - vie ( Mételin , Chio et Ténédos ) , enlin celle des tapis communs ( Imbros ) .",
        "words": [
          "odorante",
          "parfumer",
          "résineuse",
          "gomme"
        ]
      },
      {
        "@id": "http://data.odeuropa.eu/source/ff7a63d6-dc8a-598c-8ac3-159245d0bec9/fragment/d39b41cc-d4c5-5c70-96cc-6d8cb467df72",
        "value": "Lin .— L ’ huile de lin a une odeur forte et désagréable .Elle est très employée dans le Levant où elle sert à l ' éclairage , là où le pétrole n ’ a pas encore pénétré .",
        "words": [
          "désagréable",
          "forte",
          "odeur",
          "huile de lin"
        ]
      },
      {
        "@id": "http://data.odeuropa.eu/source/ff7a63d6-dc8a-598c-8ac3-159245d0bec9/fragment/d5700361-fe8f-5d25-b49e-c74164136186",
        "value": ", sans compter les fritures .Dans les quartiers populeux des villes , l ’ air en est empesté .L ’ huile d ’ olive non comestible et celle qui n ’ est pas consommée dans le pays sont exportées pour les besoins de la savonnerie .",
        "words": [
          "air",
          "empesté",
          "Dans les quartiers populeux des villes"
        ]
      },
      {
        "@id": "http://data.odeuropa.eu/source/ff7a63d6-dc8a-598c-8ac3-159245d0bec9/fragment/d589194b-754d-5431-9b42-799dfc1c1fe5",
        "value": "La récolte se fait au mois d ’ août .La gomme arabique n ’ a ni odeur ni saveur , elle est cassante et se réduit facilement en poudre .Exportation .",
        "words": [
          "odeur",
          "elle",
          "gomme arabique"
        ]
      },
      {
        "@id": "http://data.odeuropa.eu/source/ff7a63d6-dc8a-598c-8ac3-159245d0bec9/fragment/dfa6cf92-7c04-539c-9882-7fabc1a20560",
        "value": "Ses graines donnent lieu à un trafic extérieur très important .Sur place , elles produisent une huile jaune verdâtre , d ' une odeur peu agréable , qui est employée surtout pour l ’ éclairage et pour la fabrication des savons mous .Coton .",
        "words": [
          "huile",
          "odeur",
          "elles",
          "peu agréable"
        ]
      },
      {
        "@id": "http://data.odeuropa.eu/source/ff7a63d6-dc8a-598c-8ac3-159245d0bec9/fragment/e20e2a5c-bee1-5c3b-8a37-af7d806effba",
        "value": "Elle se réduit en poudre par trituration , dans un mortier en fer .La scammonée est un purgatif énergique ; elle entre dans la composition des biscuits purgatifs et de l ' eau - de - vie allemande .5o Baumes .",
        "words": [
          "purgatif",
          "scammonée"
        ]
      },
      {
        "@id": "http://data.odeuropa.eu/source/ff7a63d6-dc8a-598c-8ac3-159245d0bec9/fragment/e4fcd0b1-a384-5d58-a27d-9409e62c0212",
        "value": "Lorsque le moment de faire l ' huile est arrivé , le fabricant ne peut satisfaire à la fois à toutes les demandes , et pendant qu ' il presse les premières olives , les autres attendent et se gâtent .Quand l ' huile est faite , le paysan n ' a pas toujours assez de récipients pour la recevoir ; il mélange les nouvelles avec les anciennes , et , toutes ensemble , elles prennent un goût rance et fétide .Il y a une quinzaine d ’ années , on pouvait améliorer ces huiles en les coupant avec des huiles d ’ arachide ou de coton d ’ importation étrangère ; mais les producteurs locaux ont jugé que ces huiles leur faisaient concurrence et ils sont arrivés à les faire prohiber comme nuisibles à la santé .",
        "words": [
          "fétide",
          "rance",
          "goût"
        ]
      },
      {
        "@id": "http://data.odeuropa.eu/source/ff7a63d6-dc8a-598c-8ac3-159245d0bec9/fragment/e6b58f52-04c5-5493-a752-9f17375f6bad",
        "value": "Les individus chargés de la récolte étaient exempts d ' impôts et de corvées , mais aussi quels soins ne devaient - ils pas apporter dans leur mission ! Il fallait aplanir et balayer le sol sous l ' arbre et recueillir le mastic avec des pinces .Les premières qualités étaient envoyées au sérail , où les femmes le mâchaient pour se blanchir les dents et donnera leur haleine une odeur aromatique .Il se vendait alors 18 francs le kilogramme .",
        "words": [
          "aromatique",
          "odeur",
          "haleine",
          "sérail",
          "blanchir les dents"
        ]
      },
      {
        "@id": "http://data.odeuropa.eu/source/ff7a63d6-dc8a-598c-8ac3-159245d0bec9/fragment/f5777c25-4701-59df-a544-5175d00ed393",
        "value": "La saveur est la même .Le surplus est converti en raisins secs , en pekmcz , sorte de mélasse épaisse qu ’ on obtient en faisant cuire le raisin et en une sorte d ’ eau - de - vie blanche , nommée raki , qui prend le nom de mastic , lorsqu ’ on la parfume avec la gomme résine du lentisque .Si de l ’ intérieur nous revenons à la côte , nous trouvons .",
        "words": [
          "parfume",
          "gomme résine du lentisque"
        ]
      },
      {
        "@id": "http://data.odeuropa.eu/source/ff7a63d6-dc8a-598c-8ac3-159245d0bec9/fragment/f6a5add2-ebe0-535c-88ad-c76504ceabef",
        "value": "Tabacs 294 i ü Tabacs en feuilles 294 • - a 0 - Tabacs fabriqués 2y4 VII .Sucs végétaux 3oo i ° Essence de roses et autres essences 3oo 2 ° Opium 3oi 3 ° Gommes ..",
        "words": [
          "roses",
          "essences",
          "Essence"
        ]
      },
      {
        "@id": "http://data.odeuropa.eu/source/ff7a63d6-dc8a-598c-8ac3-159245d0bec9/fragment/fb185d5f-a6e2-5cca-b977-1b839e6e357f",
        "value": "On le trouve , dès la plus haute antiquité , en Judée , d ’ où il a disparu ; puis en Egypte , d ' où il a également disparu , et enfin en Arabie , où il croît aujourd ’ hui aux environs de la Mecque et de Médine .Ce baume , de couleur blanche , possède une odeur forte , aromatique et agréable .Il doit être conservé dans des vases de plomb ou dans des flacons de cristal bouchant à l ’ émeri .",
        "words": [
          "aromatique",
          "agréable",
          "forte",
          "odeur",
          "baume"
        ]
      },
      {
        "@id": "http://data.odeuropa.eu/source/ff7a63d6-dc8a-598c-8ac3-159245d0bec9/fragment/fb62d973-fb48-59c1-a4a9-3b1e3d464344",
        "value": "Ce nouveau produit , qui usurpe le nom de beurre , n est en réalité que de la graisse .Il est d ’ une odeur nauséabonde et l ' estomac s ’ y habitue difficilement .Ce beurre , consommé par les troupes _ , se vend en Turquie suivant la qualité entre 1 , 26 et 2 francs le kilogramme .",
        "words": [
          "odeur",
          "nauséabonde"
        ]
      }
    ],
    "author": [
      {
        "@id": "http://data.odeuropa.eu/actor/33ac3402-9c4d-575a-9e5d-a0e4c738f164",
        "label": "Alfred  Martineau"
      }
    ],
    "label": "Le commerce français dans le Levant / par Alfred Martineau,...",
    "url": "https://gallica.bnf.fr/ark:/12148/bpt6k3041916z",
    "date": "1902",
    "language": "fr"
  },
  "smellSource": [
    {
      "@id": "http://data.odeuropa.eu/vocabulary/olfactory-objects/537",
      "label": "Breath"
    }
  ],
  "time": [
    {
      "@id": "http://data.odeuropa.eu/time/6c22fc6b-e1d1-57c7-a253-774753518225",
      "label": "1902",
      "begin": "1902",
      "end": "1902"
    }
  ],
  "place": [
    {
      "@id": "https://sws.geonames.org/6275295/",
      "label": "Serail"
    }
  ],
  "relevantExcerpt": "http://data.odeuropa.eu/source/ff7a63d6-dc8a-598c-8ac3-159245d0bec9/fragment/e6b58f52-04c5-5493-a752-9f17375f6bad",
  "license": "Public domain",
  "adjective": "aromatique"
}