{
  "@type": "http://data.odeuropa.eu/ontology/L11_Smell",
  "@id": "http://data.odeuropa.eu/smell/6a3c3d4d-f4f6-53d5-b404-6f20f5eae1bb",
  "@graph": "http://data.odeuropa.eu/text-annotation",
  "label": "duhteče",
  "source": {
    "@id": "http://data.odeuropa.eu/source/71b5c756-05c9-5ccd-bce7-3f54bfdb6163",
    "excerpts": [
      {
        "@id": "http://data.odeuropa.eu/source/71b5c756-05c9-5ccd-bce7-3f54bfdb6163/fragment/0f68c072-36b4-5112-9543-b4e3cdcc0d10",
        "value": "„Alma, ti si moja ...“\\r\f\\r\fNaglas je vzkliknil in nato segel na pisalno mizo po kristalno čašico, kjer so dehtele njene vijolice, in iskreno jih je pritisnil k ustnicam in vsak kelih cvetlice je pil gorkoto velike ljubezni — — —\\r\f\\r\fNekdo potrka.",
        "words": [
          "vijolice",
          "dehtele"
        ]
      },
      {
        "@id": "http://data.odeuropa.eu/source/71b5c756-05c9-5ccd-bce7-3f54bfdb6163/fragment/11471a50-99f2-53ba-ac05-7f4d89e3da8a",
        "value": "Tedaj vstopi Klešman z velikim krožnikom, obloženim z dehtečimi klobasicami.",
        "words": [
          "dehtečimi",
          "z velikim krožnikom",
          "klobasicami ."
        ]
      },
      {
        "@id": "http://data.odeuropa.eu/source/71b5c756-05c9-5ccd-bce7-3f54bfdb6163/fragment/20f98a1c-edbf-5d7e-9a56-23868c815eff",
        "value": "V jasnih majevih večerih, preplutih blaženega vonja, pa je pred kočo na hribcu naslanjala Maretka glavo na Petrove prsi.",
        "words": [
          "blaženega",
          "vonja",
          "V jasnih majevih večerih"
        ]
      },
      {
        "@id": "http://data.odeuropa.eu/source/71b5c756-05c9-5ccd-bce7-3f54bfdb6163/fragment/2d2c5c66-9108-5fa5-9093-a56734011bcb",
        "value": "Tako blaženo niso dehtele nobene vijolice, in solnce se še ni nikdar smejalo s tako sladkim smehom iznad brezkončnega baldahina.",
        "words": [
          "Tako blaženo",
          "vijolice",
          "dehtele"
        ]
      },
      {
        "@id": "http://data.odeuropa.eu/source/71b5c756-05c9-5ccd-bce7-3f54bfdb6163/fragment/33859c6b-12ee-51ca-bd58-cab8e5408d1f",
        "value": "Skozi okno je sijal zadnji večerni žarek in poljubil duhteče vijolice na mizi.",
        "words": [
          "duhteče",
          "vijolice",
          "na mizi ."
        ]
      },
      {
        "@id": "http://data.odeuropa.eu/source/71b5c756-05c9-5ccd-bce7-3f54bfdb6163/fragment/3f3ca270-95e3-526f-8b3b-0d823c7e83d0",
        "value": "Čutil je tuintam, kadar je zavel mimo njegovih lic v hitrem plesu dehteči, gorki dih Pavle, da mu pluskajo valovi do ust — do oči, da se mu bo zvrtelo in da stori nekaj, česar se morda še pokesa.",
        "words": [
          "dih",
          "dehteči",
          "Pavle"
        ]
      },
      {
        "@id": "http://data.odeuropa.eu/source/71b5c756-05c9-5ccd-bce7-3f54bfdb6163/fragment/4735b1ce-428d-5047-b9cd-fe6280d7c777",
        "value": "Čedalje bolj nervozno je odpiral steklenke, duhal, skimaval z glavo, ogledoval kirurgično orodje ter je jezno metal v predale.",
        "words": [
          "steklenke",
          "duhal"
        ]
      },
      {
        "@id": "http://data.odeuropa.eu/source/71b5c756-05c9-5ccd-bce7-3f54bfdb6163/fragment/56a4d9d9-2960-52e9-b278-61d38d5289de",
        "value": "Ali povem ti takoj, da moj sodnijski nos v tem grmovju duha še drugo divjačino!",
        "words": [
          "duha",
          "moj sodnijski nos",
          "v tem grmovju",
          "še drugo divjačino"
        ]
      },
      {
        "@id": "http://data.odeuropa.eu/source/71b5c756-05c9-5ccd-bce7-3f54bfdb6163/fragment/58ab8c9e-7e55-5f79-a0c8-aaa63ce09e6b",
        "value": "Komaj je trenutek zasanjani, kakor bi sedel na dehtečo travo po dolgem potu, že je zazvenelo zopet orožje, razvili sta se dve zastavi: Pavla — principi ...",
        "words": [
          "travo",
          "dehtečo"
        ]
      },
      {
        "@id": "http://data.odeuropa.eu/source/71b5c756-05c9-5ccd-bce7-3f54bfdb6163/fragment/67c27cb2-3587-5750-b868-1aa13aea7350",
        "value": "“\\r\f\\r\f„Kar si mi povedal, diši skoro po policiji.",
        "words": [
          "diši",
          "po policiji ."
        ]
      },
      {
        "@id": "http://data.odeuropa.eu/source/71b5c756-05c9-5ccd-bce7-3f54bfdb6163/fragment/69113df7-8bc9-5f32-b619-c187e3059bb8",
        "value": "V bujnih laseh se je svetilo nekaj briljantov, kakor bi sredi črne noči gorela kresnica v dehteči pinijevi travi.",
        "words": [
          "dehteči",
          "pinijevi travi"
        ]
      },
      {
        "@id": "http://data.odeuropa.eu/source/71b5c756-05c9-5ccd-bce7-3f54bfdb6163/fragment/959c01d4-c44e-5f1f-a8e1-d10b65b1d61b",
        "value": "Vojske zmagujejo z našo krvjo, palače se dvigajo pod našimi kladivi, vsaka skodelica juhe, vsak kos pečenke in vsaka prežganka in suha skorja, ki pride na mizo — vsaka je hčerka žuljavih rok. — Tovariši, to smo mi, to so tisti naši zaničevani žulji, ki so večjega spoštovanja vredni, nego dehteče rokavice, ki varujejo belo roko gorkega solnca.",
        "words": [
          "rokavice",
          "dehteče"
        ]
      },
      {
        "@id": "http://data.odeuropa.eu/source/71b5c756-05c9-5ccd-bce7-3f54bfdb6163/fragment/9bf5d4da-0391-56e0-9e02-f09feffbcd98",
        "value": "Vonj njenega parfuma se je pretakal po zraku, omamna gorkota je plula krog Vinkota in govoril ji je vedno tiše in tiše ...",
        "words": [
          "Vonj",
          "parfuma",
          "po zraku ,"
        ]
      },
      {
        "@id": "http://data.odeuropa.eu/source/71b5c756-05c9-5ccd-bce7-3f54bfdb6163/fragment/c2b35dea-7b96-5262-9e94-1c0bdd91319b",
        "value": "Vse je bilo svečano, pomlad je duhtela v najlepšem cvetju.",
        "words": [
          "pomlad",
          "duhtela",
          "v najlepšem cvetju ."
        ]
      },
      {
        "@id": "http://data.odeuropa.eu/source/71b5c756-05c9-5ccd-bce7-3f54bfdb6163/fragment/cfd8111e-fad8-5480-afed-d6623a7a012a",
        "value": "V mraku je dišalo po sajah.",
        "words": [
          "dima",
          "dišalo"
        ]
      },
      {
        "@id": "http://data.odeuropa.eu/source/71b5c756-05c9-5ccd-bce7-3f54bfdb6163/fragment/f0563cb0-cecc-5819-8ad2-877d21cc30f1",
        "value": "Črn stolp dima se je v brezvetrnem vzduhu dvigal visoko in se spajal s sivo meglo, ki je ležala tako nizko, da je tičal cerkveni stolp s križem v njej, kakor bi bil pribit na velikanski plafon.",
        "words": [
          "dima",
          "vzduhu",
          "visoko"
        ]
      }
    ],
    "author": [
      {
        "@id": "http://data.odeuropa.eu/actor/2edd7343-d4c3-5838-8856-77e3e773fedc",
        "label": "Saleški Finžgar, Fran"
      }
    ],
    "genre": [
      {
        "@id": "http://data.odeuropa.eu/genre/LIT",
        "label": "Novels & poetry"
      }
    ],
    "label": "Iz modernega sveta",
    "url": "http://nl.ijs.si/imp/wikivir/dl/WIKI00496-1904.html",
    "date": "1904",
    "language": "sl"
  },
  "smellSource": [
    {
      "@id": "http://data.odeuropa.eu/vocabulary/olfactory-objects/223",
      "label": "Violet"
    }
  ],
  "time": [
    {
      "@id": "http://data.odeuropa.eu/time/9866b63b-c635-5d3c-be7a-0a79520cd327",
      "label": "1904",
      "begin": "1904",
      "end": "1904"
    }
  ],
  "place": [
    {
      "@id": "https://sws.geonames.org/93501/",
      "label": "Mayzī"
    }
  ],
  "relevantExcerpt": "http://data.odeuropa.eu/source/71b5c756-05c9-5ccd-bce7-3f54bfdb6163/fragment/33859c6b-12ee-51ca-bd58-cab8e5408d1f"
}