{
  "@type": "http://data.odeuropa.eu/ontology/L11_Smell",
  "@id": "http://data.odeuropa.eu/smell/e8c53b24-d8c4-5876-b38a-81ff83c9de34",
  "@graph": "http://data.odeuropa.eu/gallica",
  "label": "odeur",
  "source": {
    "@id": "http://data.odeuropa.eu/source/7d469c39-5b6d-5d0a-a90c-5126c07d647e",
    "excerpts": [
      {
        "@id": "http://data.odeuropa.eu/source/7d469c39-5b6d-5d0a-a90c-5126c07d647e/fragment/1959c9e5-a584-5050-b58d-5a5986dde6fe",
        "value": "De lui et des siens on a dit : « Peu de familles ont fait autant d ’ honneur à la ville d ’ Aix et ont aussi bien mérité de la République des Lettres .» De son mariage , célébré en 1584 , avec Françoise Cadenet de Lamanon , il eut : François , le célèbre Solitaire du Mont Liban , où il mourut en odeur de sainteté en 1644 ; puis : VI .— Jean Galaup , seigneur de Chasteuil , également antiquaire , historien , procureur général à la cour des Comptes de Provence , mort en 1646 , ayant épousé , en 1623 , Elisabeth Puget de Saint - Marc .",
        "words": [
          "Mont Liban",
          "odeur",
          "sainteté",
          "en 1584",
          "en 1644"
        ]
      }
    ],
    "author": [
      {
        "@id": "http://data.odeuropa.eu/actor/a3dd19d2-798d-574c-b7e6-3ffbb445f1bf",
        "label": "Aymard de  Saint-Saud"
      }
    ],
    "label": "Recherches sur le Périgord et ses familles. XI, Généalogies périgourdines, 2nde série : familles d'Alesme, d'Aydie, de Belhade, du Bois, de Bourdeille... de Ségur, de Villars / par le Cte de Saint-Saud",
    "url": "https://gallica.bnf.fr/ark:/12148/bpt6k314697j",
    "date": "1925",
    "language": "fr"
  },
  "time": [
    {
      "@id": "http://data.odeuropa.eu/time/3de668b7-9c27-59a2-9fbd-e793ac1c3625",
      "label": "1644",
      "begin": "1644",
      "end": "1644"
    },
    {
      "@id": "http://data.odeuropa.eu/time/a2ee9cef-21ec-5460-8ea8-fa764e2766ca",
      "label": "1584",
      "begin": "1584",
      "end": "1584"
    }
  ],
  "place": [
    {
      "@id": "https://sws.geonames.org/273607/",
      "label": "Mohafazat Mont-Liban"
    }
  ],
  "relevantExcerpt": "http://data.odeuropa.eu/source/7d469c39-5b6d-5d0a-a90c-5126c07d647e/fragment/1959c9e5-a584-5050-b58d-5a5986dde6fe",
  "license": "Public domain",
  "adjective": "sainteté"
}