{
  "@type": "http://data.odeuropa.eu/ontology/L11_Smell",
  "@id": "http://data.odeuropa.eu/smell/48e01396-cbe1-5332-81c4-56173701aa31",
  "@graph": "http://data.odeuropa.eu/gallica",
  "label": [
    "gaz",
    "gaz asphyxiants"
  ],
  "source": {
    "@id": "http://data.odeuropa.eu/source/31aa13f7-ec39-5bd8-a904-c584762ace83",
    "excerpts": [
      {
        "@id": "http://data.odeuropa.eu/source/31aa13f7-ec39-5bd8-a904-c584762ace83/fragment/9eb8fc80-d33e-59c8-a36b-c5e41370178a",
        "value": "40 .Rhum Américain “ THOMSON ” Parfum suave .Précieux Cordial BACOT , Toulouse C 0 uronnes Moi tu air es en perles , celluloid , barbottine PRIX AFFICHÉS ULUBIE et COSÎES , GOSteS Successeur 25 , Rue de Rémusat - - TOULOUSE Le plus bel assortiment Le meilleur marché CHOIX A DOMICILE 4 l / ETïNCliLLE n 0 I ÉPARGNE _ A _ Qu .",
        "words": [
          "suave",
          "Parfum",
          "Rhum"
        ]
      },
      {
        "@id": "http://data.odeuropa.eu/source/31aa13f7-ec39-5bd8-a904-c584762ace83/fragment/ed589057-081d-5316-beb8-d94ed0218082",
        "value": "En attendant , il importe de parer au plus .pressé ! ; le premier devoir de la municipalité est d ’ obliger la Compagnie à munir d ’ un masque contre les gaz asphyxiants non seulement les platanes mais encore tous les autres arbres de Toulouse et de la région afin de limiter le danger .Si cette précaution ne donnait pas de résultat , il y aurait lieu d ’ obliger la Compagnie à nous fournir des arbres artificiels en remplacement de ceux qu ’ elle nous tue , nombre pour nombre , avec cette particularité que les feuilles de ces arbres devront être en mesure de tomber en automne et de reparaître progressivement au printemps pour ne pas nuire à la perspective .",
        "words": [
          "Toulouse",
          "gaz",
          "région",
          "gaz asphyxiants",
          "platanes"
        ]
      }
    ],
    "label": "L'Étincelle : journal humoristique illustré : paraît tous les dimanches",
    "url": "https://gallica.bnf.fr/ark:/12148/bpt6k5342420k",
    "date": "1916-02-06",
    "language": "fr"
  },
  "smellSource": [
    {
      "@id": "http://data.odeuropa.eu/vocabulary/olfactory-objects/612",
      "label": "Gas"
    }
  ],
  "time": [
    {
      "@id": "http://data.odeuropa.eu/time/4bd14205-8ec7-5b70-80c0-3672e49fa084",
      "label": "1916-02-06",
      "begin": "1916-02-06",
      "end": "1916-02-06"
    }
  ],
  "place": [
    {
      "@id": "https://sws.geonames.org/12200097/",
      "label": "Region 2"
    },
    {
      "@id": "https://sws.geonames.org/255079/",
      "label": "Platanés"
    },
    {
      "@id": "https://sws.geonames.org/2972315/",
      "label": "Toulouse"
    }
  ],
  "emotion": [
    {
      "@id": "http://data.odeuropa.eu/emotion-type/excitement",
      "label": "excitement"
    }
  ],
  "relevantExcerpt": "http://data.odeuropa.eu/source/31aa13f7-ec39-5bd8-a904-c584762ace83/fragment/ed589057-081d-5316-beb8-d94ed0218082",
  "license": "Public domain"
}